{"ts":1780483764606,"value":"```json\n{\n  \"d\": [\n    {\n      \"t\": \"חיתוך אבן לקוי לכיסוי צנרת ברז בחצר\",\n      \"ds\": \"בחצר המבנה, בין שתי הויטרינות, קיים פגם אסתטי בחיתוך האבן המשמשת לכיסוי צנרת הברז. הפגם פוגע במראה הכללי של היקף הבית ועלול להוות מפגע גם מבחינת איטום.\",\n      \"rec\": \"יש למצוא פתרון אסתטי לכיסוי הצנרת, תוך התחשבות באיטום ובמראה הבית.\",\n      \"s\": \"cosmetic\",\n      \"p\": 33,\n      \"q\": \"ממצא חיתוך האבן בשביל כיסוי צנרת הברז. מיקום חצר המבנה בין שתי הויטרינות.\",\n      \"c\": 1000\n    }\n  ]\n}\n```"}